{"services":[{"_id":"5f80dfb1adb48729ec6087f7","title":"Aliquam eget metus eget.","brief_description":"Sed egestas tincidunt justo vitae rhoncus. Nullam aliquam pharetra leo nec vulputate. Vivamus non co","price":3030,"img":"https://image.winudf.com/v2/image/Y29tLmZyZWUud2FsbHBhcGVycy5jb29sLmhkX3NjcmVlbl8yX3EyY200aThv/screen-2.jpg?fakeurl=1&type=.jpg","description":"Aliquam eget metus eget risus sagittis imperdiet id a nunc. Donec commodo lacus non tortor hendrerit vehicula. Mauris non elit quis velit sagittis interdum sed a urna. Maecenas vel porttitor urna, sed interdum lorem. Pellentesque vehicula quam eu ex bibendum, in mollis nisl efficitur. Mauris venenatis lacinia consectetur. Ut pulvinar mollis augue viverra malesuada. Proin imperdiet eget diam ac viverra.\r\n\r\nSed egestas tincidunt justo vitae rhoncus. Nullam aliquam pharetra leo nec vulputate. Vivamus non congue purus. Nulla feugiat pulvinar diam in cursus. Proin pharetra enim eget magna elementum maximus. Nam lobortis eleifend consequat. Ut non massa nisi. Etiam non tincidunt urna. Nulla facilisi. Quisque condimentum at quam vel dignissim. Pellentesque vitae orci et tortor porta interdum id sit amet mauris. Vivamus eleifend ante vitae viverra dapibus. Quisque luctus varius sapien, et laoreet magna pulvinar in.\r\n\r\nNam a lorem mollis, facilisis libero a, egestas purus. Fusce ac sem ipsum. Nullam dui dui, finibus eu elit nec, porta sollicitudin mi. Integer consectetur quam quis facilisis convallis. Ut enim elit, facilisis id consectetur non, mattis eget dui. Nam nec accumsan turpis. Nulla facilisi. Orci varius natoque penatibus et magnis dis parturient montes, nascetur ridiculus mus. Suspendisse in odio eget dui malesuada rhoncus. Nunc pharetra pharetra erat, ac dapibus est interdum eget. Sed at sapien tellus. Sed semper, ex nec lobortis tempus, turpis lectus vestibulum sem, eu congue metus nisi ac elit.","__v":0,"count":7}],"price":6310}